codecomplexity/__init__.py
codecomplexity/analyzer.py
codecomplexity/cli.py
tests/__init__.py
tests/test_analyzer.py
codecomplexity-0.1.2.dist-info/METADATA
codecomplexity-0.1.2.dist-info/WHEEL
codecomplexity-0.1.2.dist-info/entry_points.txt
codecomplexity-0.1.2.dist-info/top_level.txt
codecomplexity-0.1.2.dist-info/RECORD
