Metadata-Version: 2.4
Name: codecomplexity
Version: 0.1.2
Summary: A simple code complexity analyzer for Python
Home-page: https://github.com/yourusername/codecomplexity
Author: Your Name
Author-email: Ayaan Bandey <ayaanniaz@gmail.com>
License: MIT
Project-URL: Homepage, https://github.com/ayaanniaz/codecomplexity
Project-URL: Bug Tracker, https://github.com/ayaanniaz/codecomplexity/issues
Classifier: Development Status :: 3 - Alpha
Classifier: Intended Audience :: Developers
Classifier: Topic :: Software Development :: Quality Assurance
Classifier: License :: OSI Approved :: MIT License
Classifier: Programming Language :: Python :: 3
Classifier: Programming Language :: Python :: 3.8
Classifier: Programming Language :: Python :: 3.9
Classifier: Programming Language :: Python :: 3.10
Classifier: Programming Language :: Python :: 3.11
Classifier: Programming Language :: Python :: 3.12
Requires-Python: >=3.8
Dynamic: author
Dynamic: home-page
Dynamic: requires-python
